pageviewapi/__init__.py
pageviewapi/client.py
pageviewapi/period.py
pageviewapi-0.4.0.dist-info/DESCRIPTION.rst
pageviewapi-0.4.0.dist-info/LICENSE.txt
pageviewapi-0.4.0.dist-info/METADATA
pageviewapi-0.4.0.dist-info/RECORD
pageviewapi-0.4.0.dist-info/WHEEL
pageviewapi-0.4.0.dist-info/metadata.json
pageviewapi-0.4.0.dist-info/top_level.txt
