Metadata-Version: 2.0
Name: pageviewapi
Version: 0.4.0
Summary: Wikimedia Pageview API client
Home-page: http://github.com/Commonists/pageview-api
Author: Commonists
Author-email: ps.huard@gmail.com
License: MIT
Platform: UNKNOWN
Classifier: Development Status :: 4 - Beta
Classifier: Environment :: Console
Classifier: Intended Audience :: Developers
Classifier: License :: OSI Approved :: MIT License
Classifier: Operating System :: OS Independent
Classifier: Programming Language :: Python
Classifier: Topic :: Utilities
Requires-Dist: requests
Requires-Dist: attrdict
